{
  "lista": [
    {
      "gameId": "001",
      "playerId": "",
      "level": 1,
      "dataType": "specie_data",
      "FechaInterna": "7/8/2022 5:29:01 PM",
      "data": {
        "specieId": "34",
        "show_desc_date": "7/8/2022 5:29:01 PM"
      }
    },
    {
      "gameId": "001",
      "playerId": "",
      "level": 1,
      "dataType": "game_data",
      "FechaInterna": "7/8/2022 5:29:24 PM",
      "data": {
        "Start_Date": "7/8/2022 5:28:42 PM",
        "End_Date": "7/8/2022 5:29:24 PM",
        "duration": 1,
        "score": 0,
        "NumberImages": 1
      }
    }
  ]
}